{
  "version": "3.0",
  "category": "quantum",
  "category_name": "量子计算",
  "total": 5,
  "updated": "2026-05-02T21:38:12.274249+08:00",
  "news": [
    {
      "id": "920621e380412e",
      "url": "https://thequantuminsider.com/2026/05/02/ionq-ceo-says-2025-marked-turning-point-for-quantum-commercialization/",
      "title": "IonQ CEO Says 2025 Marked Turning Point for Quantum Commercialization",
      "summary": "Insider Brief IonQ is positioning itself as a full-stack quantum technology provider with growing commercial traction, arguing that recent technical and financial milestones mark a turning point for the industry, according to its latest ann",
      "content": "Insider Brief IonQ is positioning itself as a full-stack quantum technology provider with growing commercial traction, arguing that recent technical and financial milestones mark a turning point for the industry, according to its latest ann",
      "category": "quantum",
      "tags": [
        "quantum"
      ],
      "publish_time": "2026-05-02T20:36:18+08:00",
      "sources": [
        {
          "name": "The Quantum Insider",
          "url": "https://thequantuminsider.com/2026/05/02/ionq-ceo-says-2025-marked-turning-point-for-quantum-commercialization/",
          "verified": true,
          "verify_time": "2026-05-02T21:37:52.647459+08:00",
          "credibility": 78
        }
      ],
      "stocks": [
        {
          "symbol": "IONQ",
          "name": "IonQ",
          "exchange": "NYSE",
          "impact": "neutral",
          "reason": "标题/摘要直接提及",
          "confidence": "direct"
        }
      ],
      "metrics": {
        "views": 0,
        "shares": 0,
        "saves": 0,
        "credibility_score": 78,
        "opportunity_score": 51
      },
      "status": "published"
    },
    {
      "id": "f71795668c0c88",
      "url": "https://quantumcomputingreport.com/house-committee-passes-their-version-of-the-u-s-national-quantum-initiative-reauthorization-act/",
      "title": "House Committee Passes Their Version of the U.S. National Quantum Initiative Reauthorization Act",
      "summary": "A couple of weeks ago we reported that the U.S. Senate Committee on Commerce, Science, and Transportation had passed S.3597 - National Quantum Initiative Reauthorization Act of 2026 and it will now be up to vote by the full Senate. Similarl",
      "content": "A couple of weeks ago we reported that the U.S. Senate Committee on Commerce, Science, and Transportation had passed S.3597 - National Quantum Initiative Reauthorization Act of 2026 and it will now be up to vote by the full Senate. Similarl",
      "category": "quantum",
      "tags": [
        "quantum"
      ],
      "publish_time": "2026-05-02T08:09:09+08:00",
      "sources": [
        {
          "name": "Quantum Computing Report",
          "url": "https://quantumcomputingreport.com/house-committee-passes-their-version-of-the-u-s-national-quantum-initiative-reauthorization-act/",
          "verified": true,
          "verify_time": "2026-05-02T21:37:53.303932+08:00",
          "credibility": 80
        }
      ],
      "stocks": [
        {
          "symbol": "IBM",
          "name": "IBM",
          "exchange": "NYSE",
          "impact": "neutral",
          "reason": "板块弱关联：量子计算",
          "confidence": "sector"
        },
        {
          "symbol": "IONQ",
          "name": "IonQ",
          "exchange": "NYSE",
          "impact": "neutral",
          "reason": "板块弱关联：量子计算",
          "confidence": "sector"
        }
      ],
      "metrics": {
        "views": 0,
        "shares": 0,
        "saves": 0,
        "credibility_score": 80,
        "opportunity_score": 27
      },
      "status": "published"
    },
    {
      "id": "e7f123782e8b45",
      "url": "https://thequantuminsider.com/2026/05/01/u-s-quantum-policy-bill-advances-to-full-house-consideration/",
      "title": "U.S. Quantum Policy Bill Advances to Full House Consideration",
      "summary": "Insider Brief The U.S. House Committee on Science, Space, and Technology has advanced legislation that would extend and update the federal government’s quantum technology strategy, moving the effort one step closer to a full House vote, acc",
      "content": "Insider Brief The U.S. House Committee on Science, Space, and Technology has advanced legislation that would extend and update the federal government’s quantum technology strategy, moving the effort one step closer to a full House vote, acc",
      "category": "quantum",
      "tags": [
        "quantum"
      ],
      "publish_time": "2026-05-01T16:18:00+08:00",
      "sources": [
        {
          "name": "The Quantum Insider",
          "url": "https://thequantuminsider.com/2026/05/01/u-s-quantum-policy-bill-advances-to-full-house-consideration/",
          "verified": true,
          "verify_time": "2026-05-02T21:37:52.649358+08:00",
          "credibility": 78
        }
      ],
      "stocks": [
        {
          "symbol": "IBM",
          "name": "IBM",
          "exchange": "NYSE",
          "impact": "neutral",
          "reason": "板块弱关联：量子计算",
          "confidence": "sector"
        },
        {
          "symbol": "IONQ",
          "name": "IonQ",
          "exchange": "NYSE",
          "impact": "neutral",
          "reason": "板块弱关联：量子计算",
          "confidence": "sector"
        }
      ],
      "metrics": {
        "views": 0,
        "shares": 0,
        "saves": 0,
        "credibility_score": 78,
        "opportunity_score": 25
      },
      "status": "published"
    },
    {
      "id": "2e5c2995ec4173",
      "url": "https://quantumcomputingreport.com/groove-quantum-secures-e16-million-18-7m-usd-to-scale-germanium-spin-qubits-debuts-18-qubit-processor/",
      "title": "Groove Quantum Secures €16 Million ($18.7M USD) to Scale Germanium Spin-Qubits; Debuts 18-Qubit Processor",
      "summary": "Groove Quantum, a spin-out from the Delft University of Technology (TU Delft) has secured €16 million ($18.7M USD) in combined equity and grants to accelerate the development of its germanium-based quantum processors. Alongside the funding,",
      "content": "Groove Quantum, a spin-out from the Delft University of Technology (TU Delft) has secured €16 million ($18.7M USD) in combined equity and grants to accelerate the development of its germanium-based quantum processors. Alongside the funding,",
      "category": "quantum",
      "tags": [
        "quantum",
        "qubit"
      ],
      "publish_time": "2026-05-01T03:10:21+08:00",
      "sources": [
        {
          "name": "Quantum Computing Report",
          "url": "https://quantumcomputingreport.com/groove-quantum-secures-e16-million-18-7m-usd-to-scale-germanium-spin-qubits-debuts-18-qubit-processor/",
          "verified": true,
          "verify_time": "2026-05-02T21:37:53.304109+08:00",
          "credibility": 80
        }
      ],
      "stocks": [
        {
          "symbol": "IBM",
          "name": "IBM",
          "exchange": "NYSE",
          "impact": "neutral",
          "reason": "板块弱关联：量子计算",
          "confidence": "sector"
        },
        {
          "symbol": "IONQ",
          "name": "IonQ",
          "exchange": "NYSE",
          "impact": "neutral",
          "reason": "板块弱关联：量子计算",
          "confidence": "sector"
        }
      ],
      "metrics": {
        "views": 0,
        "shares": 0,
        "saves": 0,
        "credibility_score": 80,
        "opportunity_score": 27
      },
      "status": "published"
    },
    {
      "id": "b6e2f74588941d",
      "url": "https://thequantuminsider.com/2026/04/30/researchers-demonstrate-ultra-low-noise-levels-of-new-qubit-platform/",
      "title": "Researchers Demonstrate Ultra-low Noise Levels of New Qubit Platform",
      "summary": "Insider Brief PRESS RELEASE — Quantum bits (qubits) are the fundamental building blocks of quantum information processing. A novel qubit platform invented at the U.S. Department of Energy’s (DOE) Argonne National Laboratory exhibits noise l",
      "content": "Insider Brief PRESS RELEASE — Quantum bits (qubits) are the fundamental building blocks of quantum information processing. A novel qubit platform invented at the U.S. Department of Energy’s (DOE) Argonne National Laboratory exhibits noise l",
      "category": "quantum",
      "tags": [
        "quantum",
        "qubit"
      ],
      "publish_time": "2026-04-30T21:43:27+08:00",
      "sources": [
        {
          "name": "The Quantum Insider",
          "url": "https://thequantuminsider.com/2026/04/30/researchers-demonstrate-ultra-low-noise-levels-of-new-qubit-platform/",
          "verified": true,
          "verify_time": "2026-05-02T21:37:52.649496+08:00",
          "credibility": 78
        }
      ],
      "stocks": [
        {
          "symbol": "IBM",
          "name": "IBM",
          "exchange": "NYSE",
          "impact": "neutral",
          "reason": "板块弱关联：量子计算",
          "confidence": "sector"
        },
        {
          "symbol": "IONQ",
          "name": "IonQ",
          "exchange": "NYSE",
          "impact": "neutral",
          "reason": "板块弱关联：量子计算",
          "confidence": "sector"
        }
      ],
      "metrics": {
        "views": 0,
        "shares": 0,
        "saves": 0,
        "credibility_score": 78,
        "opportunity_score": 25
      },
      "status": "published"
    }
  ]
}